<?xml version="1.0" encoding="utf-8" ?>

<collections>
  <collection>
    <name>Aasimar</name>
    <entry>Darkvision#60##0##0#False</entry>
    <entry>Energy Resistance#5#Acid#1#Round#0#False</entry>
    <entry>Energy Resistance#5#Cold#1#Round#0#False</entry>
    <entry>Energy Resistance#5#Electricity#1#Round#0#False</entry>
    <entry>Skill Bonus#2#Spot#0##0#False</entry>
    <entry>Skill Bonus#2#Listen#0##0#False</entry>
    <entry>Spell-Like Ability#0#Daylight#1#Day#0#False</entry>
  </collection>
  <collection>
    <name>Aboleth</name>
    <entry>Mucus Cloud#0##0##0#False</entry>
    <entry>Spell-Like Ability#0#Hypnotic pattern#0#At Will#0#False</entry>
    <entry>Spell-Like Ability#0#Illusory wall#0#At Will#0#False</entry>
    <entry>Spell-Like Ability#0#Mirage arcana#0#At Will#0#False</entry>
    <entry>Spell-Like Ability#0#Persistent image#0#At Will#0#False</entry>
    <entry>Spell-Like Ability#0#Programmed image#0#At Will#0#False</entry>
    <entry>Spell-Like Ability#0#Project image#0#At Will#0#False</entry>
  </collection>
  <collection>
    <name>Aberration</name>
    <entry>Darkvision#60##0##0#False</entry>
    <entry>Simple Weapon Proficiency#0#All#0##0#True</entry>
    <entry>Shield Proficiency#0##0##0#True</entry>
  </collection>
  <collection>
    <name>Abyssal Greater Basilisk</name>
    <entry>Damage Reduction#10#Vulnerable to magic weapons#1#Hit#0#False</entry>
    <entry>Darkvision#60##0##0#False</entry>
    <entry>Energy Resistance#10#Cold#1#Round#0#False</entry>
    <entry>Energy Resistance#10#Fire#1#Round#0#False</entry>
    <entry>Low-Light Vision#0##0##0#False</entry>
    <entry>Skill Bonus#4#Hide: in natural settings#0##0#False</entry>
    <entry>Spell Resistance#23##0##0#False</entry>
  </collection>
  <collection>
    <name>Achaierai</name>
    <entry>Darkvision#60##0##0#False</entry>
    <entry>Spell Resistance#19##0##0#False</entry>
  </collection>
  <collection>
    <name>Adult Arrowhawk</name>
    <entry>Darkvision#60##0##0#False</entry>
    <entry>Energy Resistance#10#Cold#1#Round#0#False</entry>
    <entry>Energy Resistance#10#Fire#1#Round#0#False</entry>
    <entry>Immunity#0#Acid#0##0#False</entry>
    <entry>Immunity#0#Electricity#0##0#False</entry>
    <entry>Immunity#0#Poison#0##0#False</entry>
    <entry>Skill Bonus#2#Survival: following tracks#0##0#False</entry>
    <entry>Skill Bonus#2#Survival: on Plane of Air#0##0#False</entry>
    <entry>Skill Bonus#2#Use Rope: with bindings#0##0#False</entry>
  </collection>
  <collection>
    <name>Adult Tojanida</name>
    <entry>All-Around Vision#0##0##0#False</entry>
    <entry>Darkvision#60##0##0#False</entry>
    <entry>Energy Resistance#10#Electricity#1#Round#0#False</entry>
    <entry>Energy Resistance#10#Fire#1#Round#0#False</entry>
    <entry>Immunity#0#Acid#0##0#False</entry>
    <entry>Immunity#0#Cold#0##0#False</entry>
    <entry>Immunity#0#Poison#0##0#False</entry>
    <entry>Skill Bonus#2#Survival: following tracks#0##0#False</entry>
    <entry>Skill Bonus#2#Survival: on other planes#0##0#False</entry>
    <entry>Skill Bonus#8#Swim: special action or avoid a hazard#0##0#False</entry>
    <entry>Skill Bonus#10#Swim: can always take 10#0##0#False</entry>
    <entry>Skill Bonus#2#Use Rope: with bindings#0##0#False</entry>
  </collection>
  <collection>
    <name>Air</name>
  </collection>
  <collection>
    <name>Air Elemental, Elder</name>
    <entry>Darkvision#60##0##0#False</entry>
    <entry>Damage Reduction#10#No physical vulnerabilities#1#Hit#0#False</entry>
    <entry>Immunity#0#Critical hits#0##0#False</entry>
    <entry>Immunity#0#Flanking#0##0#False</entry>
    <entry>Immunity#0#Paralysis#0##0#False</entry>
    <entry>Immunity#0#Poison#0##0#False</entry>
    <entry>Immunity#0#Sleep#0##0#False</entry>
    <entry>Immunity#0#Stunning#0##0#False</entry>
  </collection>
  <collection>
    <name>Air Elemental, Greater</name>
    <entry>Darkvision#60##0##0#False</entry>
    <entry>Damage Reduction#10#No physical vulnerabilities#1#Hit#0#False</entry>
    <entry>Immunity#0#Critical hits#0##0#False</entry>
    <entry>Immunity#0#Flanking#0##0#False</entry>
    <entry>Immunity#0#Paralysis#0##0#False</entry>
    <entry>Immunity#0#Poison#0##0#False</entry>
    <entry>Immunity#0#Sleep#0##0#False</entry>
    <entry>Immunity#0#Stunning#0##0#False</entry>
  </collection>
  <collection>
    <name>Air Elemental, Huge</name>
    <entry>Darkvision#60##0##0#False</entry>
    <entry>Damage Reduction#5#No physical vulnerabilities#1#Hit#0#False</entry>
    <entry>Immunity#0#Critical hits#0##0#False</entry>
    <entry>Immunity#0#Flanking#0##0#False</entry>
    <entry>Immunity#0#Paralysis#0##0#False</entry>
    <entry>Immunity#0#Poison#0##0#False</entry>
    <entry>Immunity#0#Sleep#0##0#False</entry>
    <entry>Immunity#0#Stunning#0##0#False</entry>
  </collection>
  <collection>
    <name>Air Elemental, Large</name>
    <entry>Darkvision#60##0##0#False</entry>
    <entry>Damage Reduction#5#No physical vulnerabilities#1#Hit#0#False</entry>
    <entry>Immunity#0#Critical hits#0##0#False</entry>
    <entry>Immunity#0#Flanking#0##0#False</entry>
    <entry>Immunity#0#Paralysis#0##0#False</entry>
    <entry>Immunity#0#Poison#0##0#False</entry>
    <entry>Immunity#0#Sleep#0##0#False</entry>
    <entry>Immunity#0#Stunning#0##0#False</entry>
  </collection>
  <collection>
    <name>Air Elemental, Medium</name>
    <entry>Darkvision#60##0##0#False</entry>
    <entry>Immunity#0#Critical hits#0##0#False</entry>
    <entry>Immunity#0#Flanking#0##0#False</entry>
    <entry>Immunity#0#Paralysis#0##0#False</entry>
    <entry>Immunity#0#Poison#0##0#False</entry>
    <entry>Immunity#0#Sleep#0##0#False</entry>
    <entry>Immunity#0#Stunning#0##0#False</entry>
  </collection>
  <collection>
    <name>Air Elemental, Small</name>
    <entry>Darkvision#60##0##0#False</entry>
    <entry>Immunity#0#Critical hits#0##0#False</entry>
    <entry>Immunity#0#Flanking#0##0#False</entry>
    <entry>Immunity#0#Paralysis#0##0#False</entry>
    <entry>Immunity#0#Poison#0##0#False</entry>
    <entry>Immunity#0#Sleep#0##0#False</entry>
    <entry>Immunity#0#Stunning#0##0#False</entry>
  </collection>
  <collection>
    <name>Air Mephit</name>
    <entry>Damage Reduction#5#Vulnerable to magic weapons#1#Hit#0#False</entry>
    <entry>Darkvision#60##0##0#False</entry>
    <entry>Fast Healing#2#Exposed to moving air#1#Turn#0#False</entry>
    <entry>Skill Bonus#2#Disguise: while acting#0##0#False</entry>
    <entry>Skill Bonus#2#Use Rope: with bindings#0##0#False</entry>
    <entry>Spell-Like Ability#0#Blur#1#Hour#0#False</entry>
    <entry>Spell-Like Ability#0#Gust of wind#1#Day#0#False</entry>
  </collection>
  <collection>
    <name>Allip</name>
    <entry>Darkvision#60##0##0#False</entry>
    <entry>Turn Resistance#2##0##0#False</entry>
    <entry>Immunity#0#Ability Drain#0##0#False</entry>
    <entry>Immunity#0#Critical hits#0##0#False</entry>
    <entry>Immunity#0#Death#0##0#False</entry>
    <entry>Immunity#0#Disease#0##0#False</entry>
    <entry>Immunity#0#Energy Drain#0##0#False</entry>
    <entry>Immunity#0#Exhaustion#0##0#False</entry>
    <entry>Immunity#0#Fatigue#0##0#False</entry>
    <entry>Immunity#0#Mind-Affecting Effects#0##0#False</entry>
    <entry>Immunity#0#Nonlethal damage#0##0#False</entry>
    <entry>Immunity#0#Nonmagical attacks#0##0#False</entry>
    <entry>Immunity#0#Paralysis#0##0#False</entry>
    <entry>Immunity#0#Poison#0##0#False</entry>
    <entry>Immunity#0#Sleep#0##0#False</entry>
    <entry>Immunity#0#Stunning#0##0#False</entry>
  </collection>
  <collection>
    <name>Androsphinx</name>
    <entry>Darkvision#60##0##0#False</entry>
    <entry>Low-Light Vision#0##0##0#False</entry>
  </collection>
  <collection>
    <name>Angel</name>
    <entry>Darkvision#60##0##0#False</entry>
    <entry>Energy Resistance#10#Electricity#1#Round#0#False</entry>
    <entry>Energy Resistance#10#Fire#1#Round#0#False</entry>
    <entry>Immunity#0#Acid#0##0#False</entry>
    <entry>Immunity#0#Cold#0##0#False</entry>
    <entry>Immunity#0#Petrification#0##0#False</entry>
    <entry>Low-Light Vision#0##0##0#False</entry>
    <entry>Protective Aura#0##0##0#False</entry>
    <entry>Save Bonus#4#Fortitude: against poison#0##0#False</entry>
    <entry>Spell-Like Ability#0#Tongues#0#Constant#0#False</entry>
  </collection>
  <collection>
    <name>Angel, Astral Deva</name>
    <entry>Change Shape#0#Small or Medium Humanoid#0##0#False</entry>
    <entry>Damage Reduction#10#Vulnerable to evil#1#Hit#0#False</entry>
    <entry>Skill Bonus#2#Use Rope: with bindings#0##0#False</entry>
    <entry>Spell Resistance#30##0##0#False</entry>
    <entry>Spell-Like Ability#0#Aid#0#At Will#0#False</entry>
    <entry>Spell-Like Ability#0#Blade barrier#1#Day#0#False</entry>
    <entry>Spell-Like Ability#0#Continual flame#0#At Will#0#False</entry>
    <entry>Spell-Like Ability#0#Cure/inflict light wounds#7#Day#0#False</entry>
    <entry>Spell-Like Ability#0#Detect chaos/law/good/evil#0#At Will#0#False</entry>
    <entry>Spell-Like Ability#0#Discern lies#0#At Will#0#False</entry>
    <entry>Spell-Like Ability#0#Dispel good/evil/law/chaos#0#At Will#0#False</entry>
    <entry>Spell-Like Ability#0#Dispel magic#0#At Will#0#False</entry>
    <entry>Spell-Like Ability#0#Heal/Harm#1#Day#0#False</entry>
    <entry>Spell-Like Ability#0#Holy aura#0#At Will#0#False</entry>
    <entry>Spell-Like Ability#0#Holy smite#0#At Will#0#False</entry>
    <entry>Spell-Like Ability#0#Holy word#0#At Will#0#False</entry>
    <entry>Spell-Like Ability#0#Invisibility (self only)#0#At Will#0#False</entry>
    <entry>Spell-Like Ability#0#Plane shift#0#At Will#0#False</entry>
    <entry>Spell-Like Ability#0#Remove curse#0#At Will#0#False</entry>
    <entry>Spell-Like Ability#0#Remove disease#0#At Will#0#False</entry>
    <entry>Spell-Like Ability#0#Remove fear#0#At Will#0#False</entry>
    <entry>Spell-Like Ability#0#See invisibility#7#Day#0#False</entry>
    <entry>Uncanny Dodge#0##0##0#False</entry>
  </collection>
  <collection>
    <name>Angel, Planetar</name>
    <entry>Change Shape#0#Small or Medium Humanoid#0##0#False</entry>
    <entry>Damage Reduction#10#Vulnerable to evil#1#Hit#0#False</entry>
    <entry>Regeneration#10#Does not regenerate evil damage#1#Round#0#False</entry>
    <entry>Skill Bonus#2#Use Rope: with bindings#0##0#False</entry>
    <entry>Spell Resistance#30##0##0#False</entry>
    <entry>Spell-Like Ability#0#Blade barrier#3#Day#0#False</entry>
    <entry>Spell-Like Ability#0#Continual flame#0#At Will#0#False</entry>
    <entry>Spell-Like Ability#0#Detect chaos/law/good/evil#0#Constant#0#False</entry>
    <entry>Spell-Like Ability#0#Detect snares and pits#0#Constant#0#False</entry>
    <entry>Spell-Like Ability#0#Discern lies#0#Constant#0#False</entry>
    <entry>Spell-Like Ability#0#Dispel magic#0#At Will#0#False</entry>
    <entry>Spell-Like Ability#0#Earthquake#1#Day#0#False</entry>
    <entry>Spell-Like Ability#0#Flame strike#3#Day#0#False</entry>
    <entry>Spell-Like Ability#0#Greater restoration#1#Day#0#False</entry>
    <entry>Spell-Like Ability#0#Holy smite#0#At Will#0#False</entry>
    <entry>Spell-Like Ability#0#Invisibility (self only)#0#At Will#0#False</entry>
    <entry>Spell-Like Ability#0#Lesser restoration#0#At Will#0#False</entry>
    <entry>Spell-Like Ability#0#Mass charm monster#1#Day#0#False</entry>
    <entry>Spell-Like Ability#0#Power word stun#3#Day#0#False</entry>
    <entry>Spell-Like Ability#0#Raise dead#3#Day#0#False</entry>
    <entry>Spell-Like Ability#0#Remove curse#0#At Will#0#False</entry>
    <entry>Spell-Like Ability#0#Remove disease#0#At Will#0#False</entry>
    <entry>Spell-Like Ability#0#Remove fear#0#At Will#0#False</entry>
    <entry>Spell-Like Ability#0#See invisibility#0#Constant#0#False</entry>
    <entry>Spell-Like Ability#0#Speak with dead#0#At Will#0#False</entry>
    <entry>Spell-Like Ability#0#True seeing#0#Constant#0#False</entry>
    <entry>Spell-Like Ability#0#Waves of exhaustion#1#Day#0#False</entry>
    <entry>Spell-Like Ability#0#Waves of fatigue#3#Day#0#False</entry>
  </collection>
  <collection>
    <name>Angel, Solar</name>
    <entry>Change Shape#0#Small or Medium Humanoid#0##0#False</entry>
    <entry>Damage Reduction#15#Vulnerable to epic evil#1#Hit#0#False</entry>
    <entry>Regeneration#15#Does not regenerate evil damage#1#Round#0#False</entry>
    <entry>Skill Bonus#2#Survival: following tracks#0##0#False</entry>
    <entry>Skill Bonus#2#Use Rope: with bindings#0##0#False</entry>
    <entry>Spell Resistance#32##0##0#False</entry>
    <entry>Spell-Like Ability#0#Aid#0#At Will#0#False</entry>
    <entry>Spell-Like Ability#0#Animate objects#0#At Will#0#False</entry>
    <entry>Spell-Like Ability#0#Blade barrier#3#Day#0#False</entry>
    <entry>Spell-Like Ability#0#Commune#0#At Will#0#False</entry>
    <entry>Spell-Like Ability#0#Continual flame#0#At Will#0#False</entry>
    <entry>Spell-Like Ability#0#Detect chaos/law/good/evil#0#Constant#0#False</entry>
    <entry>Spell-Like Ability#0#Detect snares and pits#0#Constant#0#False</entry>
    <entry>Spell-Like Ability#0#Dimensional anchor#0#At Will#0#False</entry>
    <entry>Spell-Like Ability#0#Discern lies#0#Constant#0#False</entry>
    <entry>Spell-Like Ability#0#Earthquake#3#Day#0#False</entry>
    <entry>Spell-Like Ability#0#Greater dispel magic#0#At Will#0#False</entry>
    <entry>Spell-Like Ability#0#Greater restoration#1#Day#0#False</entry>
    <entry>Spell-Like Ability#0#Heal/Harm#3#Day#0#False</entry>
    <entry>Spell-Like Ability#0#Holy smite#0#At Will#0#False</entry>
    <entry>Spell-Like Ability#0#Imprisonment#0#At Will#0#False</entry>
    <entry>Spell-Like Ability#0#Invisibility (self only)#0#At Will#0#False</entry>
    <entry>Spell-Like Ability#0#Lesser restoration#0#At Will#0#False</entry>
    <entry>Spell-Like Ability#0#Mass charm monster#3#Day#0#False</entry>
    <entry>Spell-Like Ability#0#Permanency#3#Day#0#False</entry>
    <entry>Spell-Like Ability#0#Power word blind#1#Day#0#False</entry>
    <entry>Spell-Like Ability#0#Power word kill#1#Day#0#False</entry>
    <entry>Spell-Like Ability#0#Power word stun#1#Day#0#False</entry>
    <entry>Spell-Like Ability#0#Prismatic spray#1#Day#0#False</entry>
    <entry>Spell-Like Ability#0#Remove curse#0#At Will#0#False</entry>
    <entry>Spell-Like Ability#0#Remove disease#0#At Will#0#False</entry>
    <entry>Spell-Like Ability#0#Remove fear#0#At Will#0#False</entry>
    <entry>Spell-Like Ability#0#Resist energy#0#At Will#0#False</entry>
    <entry>Spell-Like Ability#0#Resurrection#3#Day#0#False</entry>
    <entry>Spell-Like Ability#0#See invisibility#0#Constant#0#False</entry>
    <entry>Spell-Like Ability#0#Speak with dead#0#At Will#0#False</entry>
    <entry>Spell-Like Ability#0#Summon monster VII#0#At Will#0#False</entry>
    <entry>Spell-Like Ability#0#True seeing#0#Constant#0#False</entry>
    <entry>Spell-Like Ability#0#Waves of exhaustion#3#Day#0#False</entry>
    <entry>Spell-Like Ability#0#Waves of fatigue#0#At Will#0#False</entry>
    <entry>Spell-Like Ability#0#Wish#1#Day#0#False</entry>
  </collection>
  <collection>
    <name>Animal</name>
    <entry>Low-Light Vision#0##0##0#False</entry>
  </collection>
  <collection>
    <name>Animated Object, Colossal</name>
  </collection>
  <collection>
    <name>Animated Object, Gargantuan</name>
  </collection>
  <collection>
    <name>Animated Object, Huge</name>
  </collection>
  <collection>
    <name>Animated Object, Large</name>
  </collection>
  <collection>
    <name>Animated Object, Medium</name>
  </collection>
  <collection>
    <name>Animated Object, Small</name>
  </collection>
  <collection>
    <name>Animated Object, Tiny</name>
  </collection>
  <collection>
    <name>Ankheg</name>
    <entry>Darkvision#60##0##0#False</entry>
    <entry>Low-Light Vision#0##0##0#False</entry>
    <entry>Tremorsense#60##0##0#False</entry>
  </collection>
  <collection>
    <name>Annis</name>
    <entry>Damage Reduction#2#Vulnerable to bludgeoning weapons#1#Hit#0#False</entry>
    <entry>Darkvision#60##0##0#False</entry>
    <entry>Skill Bonus#2#Disguise: while acting#0##0#False</entry>
    <entry>Spell Resistance#19##0##0#False</entry>
    <entry>Spell-Like Ability#0#Disguise self#3#Day#0#False</entry>
    <entry>Spell-Like Ability#0#Fog cloud#3#Day#0#False</entry>
  </collection>
  <collection>
    <name>Ape</name>
    <entry>Scent#0##0##0#False</entry>
    <entry>Skill Bonus#8#Climb#0##0#False</entry>
    <entry>Skill Bonus#10#Climb: can always take 10#0##0#False</entry>
  </collection>
  <collection>
    <name>Aquatic</name>
    <entry>Skill Bonus#8#Swim: special action or avoid a hazard#0##0#False</entry>
    <entry>Skill Bonus#10#Swim: can always take 10#0##0#False</entry>
  </collection>
  <collection>
    <name>Aquatic Elf</name>
    <entry>Gills#0##0##0#False</entry>
    <entry>Immunity#0#Sleep#0##0#False</entry>
    <entry>Martial Weapon Proficiency#0#Composite longbow#0##0#True</entry>
    <entry>Martial Weapon Proficiency#0#Composite shortbow#0##0#True</entry>
    <entry>Martial Weapon Proficiency#0#Longsword#0##0#True</entry>
    <entry>Martial Weapon Proficiency#0#Longbow#0##0#True</entry>
    <entry>Martial Weapon Proficiency#0#Rapier#0##0#True</entry>
    <entry>Martial Weapon Proficiency#0#Shortbow#0##0#True</entry>
    <entry>Save Bonus#2#enchantment spells or effects#0##0#False</entry>
    <entry>Skill Bonus#2#Listen#0##0#False</entry>
    <entry>Skill Bonus#2#Search#0##0#False</entry>
    <entry>Skill Bonus#0#Search: passing within 5 feet of a secret or concealed door allows a Search check to notice it as if the door was being actively looked for#0##0#False</entry>
    <entry>Skill Bonus#2#Spot#0##0#False</entry>
    <entry>Superior Low-Light Vision#0##0##0#False</entry>
  </collection>
  <collection>
    <name>Aranea</name>
    <entry>Change Shape#0#Small or Medium humanoid; or Medium spider-human hybrid (like a Lycanthrope)#0##0#False</entry>
    <entry>Darkvision#60##0##0#False</entry>
    <entry>Low-Light Vision#0##0##0#False</entry>
    <entry>Skill Bonus#8#Climb#0##0#False</entry>
    <entry>Skill Bonus#10#Climb: can always take 10#0##0#False</entry>
    <entry>Skill Bonus#2#Jump#0##0#False</entry>
    <entry>Skill Bonus#2#Listen#0##0#False</entry>
    <entry>Skill Bonus#2#Spot#0##0#False</entry>
  </collection>
  <collection>
    <name>Archon</name>
    <entry>Aura of Menace#0##0##0#False</entry>
    <entry>Darkvision#60##0##0#False</entry>
    <entry>Immunity#0#Electricity#0##0#False</entry>
    <entry>Immunity#0#Petrification#0##0#False</entry>
    <entry>Low-Light Vision#0##0##0#False</entry>
    <entry>Save Bonus#4#Fortitude: against poison#0##0#False</entry>
    <entry>Spell-Like Ability#0#Greater teleport: self plus 50 pounds of objects only#0#At Will#0#False</entry>
    <entry>Spell-Like Ability#0#Magic circle against chaos/law/good/evil#0#Constant#0#False</entry>
    <entry>Spell-Like Ability#0#Tongues#0#Constant#0#False</entry>
  </collection>
  <collection>
    <name>Assassin Vine</name>
    <entry>Blindsight#30##0##0#False</entry>
    <entry>Camouflage#0##0##0#False</entry>
    <entry>Energy Resistance#10#Cold#1#Round#0#False</entry>
    <entry>Energy Resistance#10#Fire#1#Round#0#False</entry>
    <entry>Immunity#0#Electricity#0##0#False</entry>
    <entry>Skill Bonus#8#Climb#0##0#False</entry>
    <entry>Skill Bonus#10#Climb: can always take 10#0##0#False</entry>
  </collection>
  <collection>
    <name>Athach</name>
  </collection>
  <collection>
    <name>Augmented</name>
  </collection>
  <collection>
    <name>Average Salamander</name>
    <entry>Damage Reduction#10#Vulnerable to magic weapons#1#Hit#0#False</entry>
    <entry>Darkvision#60##0##0#False</entry>
    <entry>Immunity#0#Fire#0##0#False</entry>
    <entry>Multiattack#0##0##0#False</entry>
    <entry>Skill Bonus#4#Craft/Blacksmithing#0##0#False</entry>
    <entry>Vulnerability#0#Cold#0##0#False</entry>
  </collection>
  <collection>
    <name>Average Xorn</name>
    <entry>All-Around Vision#0##0##0#False</entry>
    <entry>Cleave#0##0##0#False</entry>
    <entry>Damage Reduction#5#Vulnerable to bludgeoning weapons#1#Hit#0#False</entry>
    <entry>Darkvision#60##0##0#False</entry>
    <entry>Earth Glide#0##0##0#False</entry>
    <entry>Energy Resistance#10#Electricity#1#Round#0#False</entry>
    <entry>Immunity#0#Cold#0##0#False</entry>
    <entry>Immunity#0#Fire#0##0#False</entry>
    <entry>Skill Bonus#2#Survival: following tracks#0##0#False</entry>
    <entry>Skill Bonus#2#Survival: underground#0##0#False</entry>
    <entry>Tremorsense#60##0##0#False</entry>
  </collection>
  <collection>
    <name>Avoral</name>
    <entry>Damage Reduction#10#Vulnerable to evil or silver weapons#1#Hit#0#False</entry>
    <entry>Darkvision#60##0##0#False</entry>
    <entry>Energy Resistance#10#Cold#1#Round#0#False</entry>
    <entry>Energy Resistance#10#Sonic#1#Round#0#False</entry>
    <entry>Immunity#0#Electricity#0##0#False</entry>
    <entry>Immunity#0#Petrification#0##0#False</entry>
    <entry>Lay on Hands#0##0##0#False</entry>
    <entry>Low-Light Vision#0##0##0#False</entry>
    <entry>Skill Bonus#2#Disguise: while acting#0##0#False</entry>
    <entry>Skill Bonus#8#Spot#0##0#False</entry>
    <entry>Spell Resistance#25##0##0#False</entry>
    <entry>Spell-Like Ability#0#Aid#0#At Will#0#False</entry>
    <entry>Spell-Like Ability#0#Blur: self only#0#At Will#0#False</entry>
    <entry>Spell-Like Ability#0#Command#0#At Will#0#False</entry>
    <entry>Spell-Like Ability#0#Detect magic#0#At Will#0#False</entry>
    <entry>Spell-Like Ability#0#Dimension door#0#At Will#0#False</entry>
    <entry>Spell-Like Ability#0#Dispel magic#0#At Will#0#False</entry>
    <entry>Spell-Like Ability#0#Gust of wind#0#At Will#0#False</entry>
    <entry>Spell-Like Ability#0#Hold person#0#At Will#0#False</entry>
    <entry>Spell-Like Ability#0#Light#0#At Will#0#False</entry>
    <entry>Spell-Like Ability#0#Lightning bolt#3#Day#0#False</entry>
    <entry>Spell-Like Ability#0#Magic circle against chaos/law/good/evil: self only#0#At Will#0#False</entry>
    <entry>Spell-Like Ability#0#Magic missile#0#At Will#0#False</entry>
    <entry>Spell-Like Ability#0#See invisibility#0#At Will#0#False</entry>
    <entry>Spell-Like Ability#0#Speak with animals#0#Constant#0#False</entry>
    <entry>Spell-Like Ability#0#True seeing#0#At Will#0#False</entry>
  </collection>
  <collection>
    <name>Azer</name>
    <entry>Darkvision#60##0##0#False</entry>
    <entry>Immunity#0#Fire#0##0#False</entry>
    <entry>Spell Resistance#13##0##0#False</entry>
    <entry>Vulnerability#0#Cold#0##0#False</entry>
  </collection>
  <collection>
    <name>Babau</name>
    <entry>Damage Reduction#10#Vulnerable to good or cold iron weapons#1#Hit#0#False</entry>
    <entry>Darkvision#60##0##0#False</entry>
    <entry>Energy Resistance#10#Acid#1#Round#0#False</entry>
    <entry>Energy Resistance#10#Cold#1#Round#0#False</entry>
    <entry>Energy Resistance#10#Fire#1#Round#0#False</entry>
    <entry>Immunity#0#Electricity#0##0#False</entry>
    <entry>Immunity#0#Poison#0##0#False</entry>
    <entry>Protective Slime#0##0##0#False</entry>
    <entry>Skill Bonus#8#Hide#0##0#False</entry>
    <entry>Skill Bonus#8#Listen#0##0#False</entry>
    <entry>Skill Bonus#8#Move Silently#0##0#False</entry>
    <entry>Skill Bonus#8#Search#0##0#False</entry>
    <entry>Spell Resistance#14##0##0#False</entry>
    <entry>Spell-Like Ability#0#Darkness#0#At Will#0#False</entry>
    <entry>Spell-Like Ability#0#Dispel magic#0#At Will#0#False</entry>
    <entry>Spell-Like Ability#0#Greater teleport: self plus 50 pounds of objects only#0#At Will#0#False</entry>
    <entry>Spell-Like Ability#0#See invisibility#0#At Will#0#False</entry>
    <entry>Telepathy#100##0##0#False</entry>
  </collection>
  <collection>
    <name>Baboon</name>
    <entry>Scent#0##0##0#False</entry>
    <entry>Skill Bonus#8#Climb#0##0#False</entry>
    <entry>Skill Bonus#10#Climb: can always take 10#0##0#False</entry>
  </collection>
  <collection>
    <name>Badger</name>
    <entry>Scent#0##0##0#False</entry>
    <entry>Skill Bonus#4#Escape Artist#0##0#False</entry>
    <entry>Track#0##0##0#False</entry>
    <entry>Weapon Finesse#0##0##0#False</entry>
  </collection>
  <collection>
    <name>Baleen Whale</name>
    <entry>Blindsight#120##0##0#False</entry>
    <entry>Hold Breath#0##0##0#False</entry>
    <entry>Skill Bonus#4#Listen#0##0#False</entry>
    <entry>Skill Bonus#4#Spot#0##0#False</entry>
  </collection>
  <collection>
    <name>Balor</name>
    <entry>Damage Reduction#15#Vulnerable to good and cold iron weapons#1#Hit#0#False</entry>
    <entry>Darkvision#60##0##0#False</entry>
    <entry>Energy Resistance#10#Acid#1#Round#0#False</entry>
    <entry>Energy Resistance#10#Cold#1#Round#0#False</entry>
    <entry>Exotic Weapon Proficiency#0#Whip#0##0#True</entry>
    <entry>Immunity#0#Electricity#0##0#False</entry>
    <entry>Flaming Body#0##0##0#False</entry>
    <entry>Immunity#0#Fire#0##0#False</entry>
    <entry>Immunity#0#Poison#0##0#False</entry>
    <entry>Skill Bonus#8#Listen#0##0#False</entry>
    <entry>Skill Bonus#8#Spot#0##0#False</entry>
    <entry>Spell Resistance#28##0##0#False</entry>
    <entry>Spell-Like Ability#0#Blasphemy#0#At Will#0#False</entry>
    <entry>Spell-Like Ability#0#Dominate monster#0#At Will#0#False</entry>
    <entry>Spell-Like Ability#0#Fire storm#1#Day#0#False</entry>
    <entry>Spell-Like Ability#0#Greater dispel magic#0#At Will#0#False</entry>
    <entry>Spell-Like Ability#0#Greater teleport: self plus 50 pounds of objects only#0#At Will#0#False</entry>
    <entry>Spell-Like Ability#0#Implosion#1#Day#0#False</entry>
    <entry>Spell-Like Ability#0#Insanity#0#At Will#0#False</entry>
    <entry>Spell-Like Ability#0#Power word stun#0#At Will#0#False</entry>
    <entry>Spell-Like Ability#0#Telekinesis#0#At Will#0#False</entry>
    <entry>Spell-Like Ability#0#True seeing#0#Constant#0#False</entry>
    <entry>Spell-Like Ability#0#Unholy aura#0#At Will#0#False</entry>
    <entry>Telepathy#100##0##0#False</entry>
  </collection>
  <collection>
    <name>Barbed Devil (Hamatula)</name>
  </collection>
  <collection>
    <name>Barghest</name>
    <entry>Change Shape#0#Goblin or wolf#0##0#False</entry>
    <entry>Damage Reduction#5#Vulnerable to magic weapons#1#Hit#0#False</entry>
    <entry>Darkvision#60##0##0#False</entry>
    <entry>Scent#0##0##0#False</entry>
    <entry>Skill Bonus#2#Disguise: while acting#0##0#False</entry>
    <entry>Skill Bonus#4#Hide: in wolf form#0##0#False</entry>
    <entry>Skill Bonus#2#Survival: following tracks#0##0#False</entry>
    <entry>Spell-Like Ability#0#Blink#0#At Will#0#False</entry>
    <entry>Spell-Like Ability#0#Charm monster#1#Day#0#False</entry>
    <entry>Spell-Like Ability#0#Crushing despair#1#Day#0#False</entry>
    <entry>Spell-Like Ability#0#Dimension door#1#Day#0#False</entry>
    <entry>Spell-Like Ability#0#Levitate#0#At Will#0#False</entry>
    <entry>Spell-Like Ability#0#Misdirection#0#At Will#0#False</entry>
    <entry>Spell-Like Ability#0#Pass without trace: in wolf form#0#At Will#0#False</entry>
    <entry>Spell-Like Ability#0#Rage#0#At Will#0#False</entry>
  </collection>
  <collection>
    <name>Basilisk</name>
    <entry>Darkvision#60##0##0#False</entry>
    <entry>Low-Light Vision#0##0##0#False</entry>
    <entry>Skill Bonus#4#Hide: in natural settings#0##0#False</entry>
  </collection>
  <collection>
    <name>Bat</name>
    <entry>Blindsense#20##0##0#False</entry>
    <entry>Skill Bonus#4#Listen#0##0#False</entry>
    <entry>Skill Bonus#4#Spot#0##0#False</entry>
  </collection>
  <collection>
    <name>Bat Swarm</name>
    <entry>Blindsense#20##0##0#False</entry>
    <entry>Immunity#0#Critical hits#0##0#False</entry>
    <entry>Immunity#0#Flanking#0##0#False</entry>
    <entry>Immunity#0#Weapon damage#0##0#False</entry>
    <entry>Skill Bonus#4#Listen#0##0#False</entry>
    <entry>Skill Bonus#4#Spot#0##0#False</entry>
  </collection>
  <collection>
    <name>Bearded Devil (Barbazu)</name>
  </collection>
  <collection>
    <name>Bebilith</name>
    <entry>Damage Reduction#10#Vulnerable to good weapons#1#Hit#0#False</entry>
    <entry>Darkvision#60##0##0#False</entry>
    <entry>Scent#0##0##0#False</entry>
    <entry>Skill Bonus#8#Hide#0##0#False</entry>
    <entry>Skill Bonus#2#Survival: following tracks#0##0#False</entry>
    <entry>Spell-Like Ability#0#Plane shift: self only#0#At Will#0#False</entry>
    <entry>Telepathy#100##0##0#False</entry>
  </collection>
  <collection>
    <name>Behir</name>
    <entry>Darkvision#60##0##0#False</entry>
    <entry>Immunity#0#Electricity#0##0#False</entry>
    <entry>Immunity#0#Tripping#0##0#False</entry>
    <entry>Low-Light Vision#0##0##0#False</entry>
    <entry>Scent#0##0##0#False</entry>
    <entry>Skill Bonus#8#Climb#0##0#False</entry>
    <entry>Skill Bonus#10#Climb: can always take 10#0##0#False</entry>
  </collection>
  <collection>
    <name>Beholder</name>
    <entry>All-Around Vision#0##0##0#False</entry>
    <entry>Antimagic Cone#0##0##0#False</entry>
    <entry>Flight#0##0##0#False</entry>
    <entry>Skill Bonus#2#Survival: following tracks#0##0#False</entry>
    <entry>Alertness#2##0##0#False</entry>
  </collection>
  <collection>
    <name>Belker</name>
    <entry>Darkvision#60##0##0#False</entry>
    <entry>Immunity#0#Critical hits#0##0#False</entry>
    <entry>Immunity#0#Flanking#0##0#False</entry>
    <entry>Immunity#0#Paralysis#0##0#False</entry>
    <entry>Immunity#0#Poison#0##0#False</entry>
    <entry>Immunity#0#Sleep#0##0#False</entry>
    <entry>Immunity#0#Stunning#0##0#False</entry>
    <entry>Skill Bonus#4#Move Silently#0##0#False</entry>
    <entry>Smoke Form#0##0##0#False</entry>
  </collection>
  <collection>
    <name>Bison</name>
    <entry>Scent#0##0##0#False</entry>
  </collection>
  <collection>
    <name>Black Bear</name>
    <entry>Scent#0##0##0#False</entry>
    <entry>Skill Bonus#4#Swim#0##0#False</entry>
  </collection>
  <collection>
    <name>Black Dragon, Adult</name>
    <entry>Blindsense#60##0##0#False</entry>
    <entry>Corrupt Water#0##1#Day#0#False</entry>
    <entry>Darkvision#120##0##0#False</entry>
    <entry>Immunity#0#Acid#0##0#False</entry>
    <entry>Immunity#0#Paralysis#0##0#False</entry>
    <entry>Immunity#0#Sleep#0##0#False</entry>
    <entry>Keen Senses#0##0##0#False</entry>
    <entry>Spell-Like Ability#0#Darkness#3#Day#0#False</entry>
    <entry>Water Breathing#0##0##0#False</entry>
  </collection>
  <collection>
    <name>Black Dragon, Ancient</name>
    <entry>Blindsense#60##0##0#False</entry>
    <entry>Corrupt Water#0##1#Day#0#False</entry>
    <entry>Damage Reduction#15#Vulnerable to magic weapons#1#Hit#0#False</entry>
    <entry>Darkvision#120##0##0#False</entry>
    <entry>Immunity#0#Acid#0##0#False</entry>
    <entry>Immunity#0#Paralysis#0##0#False</entry>
    <entry>Immunity#0#Sleep#0##0#False</entry>
    <entry>Keen Senses#0##0##0#False</entry>
    <entry>Spell-Like Ability#0#Darkness#3#Day#0#False</entry>
    <entry>Spell-Like Ability#0#Insect plague#3#Day#0#False</entry>
    <entry>Spell-Like Ability#0#Plant growth#1#Day#0#False</entry>
    <entry>Water Breathing#0##0##0#False</entry>
  </collection>
  <collection>
    <name>Black Dragon, Great Wyrm</name>
    <entry>Blindsense#60##0##0#False</entry>
    <entry>Charm Reptiles#0##3#Day#0#False</entry>
    <entry>Corrupt Water#0##1#Day#0#False</entry>
    <entry>Damage Reduction#20#Vulnerable to magic weapons#1#Hit#0#False</entry>
    <entry>Darkvision#120##0##0#False</entry>
    <entry>Immunity#0#Acid#0##0#False</entry>
    <entry>Immunity#0#Paralysis#0##0#False</entry>
    <entry>Immunity#0#Sleep#0##0#False</entry>
    <entry>Keen Senses#0##0##0#False</entry>
    <entry>Spell-Like Ability#0#Darkness#3#Day#0#False</entry>
    <entry>Spell-Like Ability#0#Insect plague#3#Day#0#False</entry>
    <entry>Spell-Like Ability#0#Plant growth#1#Day#0#False</entry>
    <entry>Water Breathing#0##0##0#False</entry>
  </collection>
  <collection>
    <name>Black Dragon, Juvenile</name>
    <entry>Blindsense#60##0##0#False</entry>
    <entry>Darkvision#120##0##0#False</entry>
    <entry>Immunity#0#Acid#0##0#False</entry>
    <entry>Immunity#0#Paralysis#0##0#False</entry>
    <entry>Immunity#0#Sleep#0##0#False</entry>
    <entry>Keen Senses#0##0##0#False</entry>
    <entry>Spell-Like Ability#0#Darkness#3#Day#0#False</entry>
    <entry>Water Breathing#0##0##0#False</entry>
  </collection>
  <collection>
    <name>Black Dragon, Mature Adult</name>
    <entry>Blindsense#60##0##0#False</entry>
    <entry>Corrupt Water#0##1#Day#0#False</entry>
    <entry>Damage Reduction#10#Vulnerable to magic weapons#1#Hit#0#False</entry>
    <entry>Darkvision#120##0##0#False</entry>
    <entry>Immunity#0#Acid#0##0#False</entry>
    <entry>Immunity#0#Paralysis#0##0#False</entry>
    <entry>Immunity#0#Sleep#0##0#False</entry>
    <entry>Keen Senses#0##0##0#False</entry>
    <entry>Spell-Like Ability#0#Darkness#3#Day#0#False</entry>
    <entry>Water Breathing#0##0##0#False</entry>
  </collection>
  <collection>
    <name>Black Dragon, Old</name>
    <entry>Blindsense#60##0##0#False</entry>
    <entry>Corrupt Water#0##1#Day#0#False</entry>
    <entry>Damage Reduction#10#Vulnerable to magic weapons#1#Hit#0#False</entry>
    <entry>Darkvision#120##0##0#False</entry>
    <entry>Immunity#0#Acid#0##0#False</entry>
    <entry>Immunity#0#Paralysis#0##0#False</entry>
    <entry>Immunity#0#Sleep#0##0#False</entry>
    <entry>Keen Senses#0##0##0#False</entry>
    <entry>Spell-Like Ability#0#Darkness#3#Day#0#False</entry>
    <entry>Spell-Like Ability#0#Plant growth#1#Day#0#False</entry>
    <entry>Water Breathing#0##0##0#False</entry>
  </collection>
  <collection>
    <name>Black Dragon, Very Old</name>
    <entry>Blindsense#60##0##0#False</entry>
    <entry>Corrupt Water#0##1#Day#0#False</entry>
    <entry>Damage Reduction#15#Vulnerable to magic weapons#1#Hit#0#False</entry>
    <entry>Darkvision#120##0##0#False</entry>
    <entry>Immunity#0#Acid#0##0#False</entry>
    <entry>Immunity#0#Paralysis#0##0#False</entry>
    <entry>Immunity#0#Sleep#0##0#False</entry>
    <entry>Keen Senses#0##0##0#False</entry>
    <entry>Spell-Like Ability#0#Darkness#3#Day#0#False</entry>
    <entry>Spell-Like Ability#0#Plant growth#1#Day#0#False</entry>
    <entry>Water Breathing#0##0##0#False</entry>
  </collection>
  <collection>
    <name>Black Dragon, Very Young</name>
    <entry>Blindsense#60##0##0#False</entry>
    <entry>Darkvision#120##0##0#False</entry>
    <entry>Immunity#0#Acid#0##0#False</entry>
    <entry>Immunity#0#Paralysis#0##0#False</entry>
    <entry>Immunity#0#Sleep#0##0#False</entry>
    <entry>Keen Senses#0##0##0#False</entry>
    <entry>Water Breathing#0##0##0#False</entry>
  </collection>
  <collection>
    <name>Black Dragon, Wyrm</name>
    <entry>Blindsense#60##0##0#False</entry>
    <entry>Corrupt Water#0##1#Day#0#False</entry>
    <entry>Damage Reduction#20#Vulnerable to magic weapons#1#Hit#0#False</entry>
    <entry>Darkvision#120##0##0#False</entry>
    <entry>Immunity#0#Acid#0##0#False</entry>
    <entry>Immunity#0#Paralysis#0##0#False</entry>
    <entry>Immunity#0#Sleep#0##0#False</entry>
    <entry>Keen Senses#0##0##0#False</entry>
    <entry>Spell-Like Ability#0#Darkness#3#Day#0#False</entry>
    <entry>Spell-Like Ability#0#Insect plague#3#Day#0#False</entry>
    <entry>Spell-Like Ability#0#Plant growth#1#Day#0#False</entry>
    <entry>Water Breathing#0##0##0#False</entry>
  </collection>
  <collection>
    <name>Black Dragon, Wyrmling</name>
    <entry>Blindsense#60##0##0#False</entry>
    <entry>Darkvision#120##0##0#False</entry>
    <entry>Immunity#0#Acid#0##0#False</entry>
    <entry>Immunity#0#Paralysis#0##0#False</entry>
    <entry>Immunity#0#Sleep#0##0#False</entry>
    <entry>Keen Senses#0##0##0#False</entry>
    <entry>Water Breathing#0##0##0#False</entry>
  </collection>
  <collection>
    <name>Black Dragon, Young Adult</name>
    <entry>Blindsense#60##0##0#False</entry>
    <entry>Damage Reduction#5#Vulnerable to magic weapons#1#Hit#0#False</entry>
    <entry>Darkvision#120##0##0#False</entry>
    <entry>Immunity#0#Acid#0##0#False</entry>
    <entry>Immunity#0#Paralysis#0##0#False</entry>
    <entry>Immunity#0#Sleep#0##0#False</entry>
    <entry>Keen Senses#0##0##0#False</entry>
    <entry>Spell-Like Ability#0#Darkness#3#Day#0#False</entry>
    <entry>Water Breathing#0##0##0#False</entry>
  </collection>
  <collection>
    <name>Black Dragon, Young</name>
    <entry>Blindsense#60##0##0#False</entry>
    <entry>Darkvision#120##0##0#False</entry>
    <entry>Immunity#0#Acid#0##0#False</entry>
    <entry>Immunity#0#Paralysis#0##0#False</entry>
    <entry>Immunity#0#Sleep#0##0#False</entry>
    <entry>Keen Senses#0##0##0#False</entry>
    <entry>Water Breathing#0##0##0#False</entry>
  </collection>
  <collection>
    <name>Black Pudding</name>
  </collection>
  <collection>
    <name>Blink Dog</name>
  </collection>
  <collection>
    <name>Blue Dragon, Adult</name>
    <entry>Poor Maneuverability</entry>
  </collection>
  <collection>
    <name>Blue Dragon, Ancient</name>
    <entry>Clumsy Maneuverability</entry>
  </collection>
  <collection>
    <name>Blue Dragon, Great Wyrm</name>
    <entry>Clumsy Maneuverability</entry>
  </collection>
  <collection>
    <name>Blue Dragon, Juvenile</name>
    <entry>Poor Maneuverability</entry>
  </collection>
  <collection>
    <name>Blue Dragon, Mature Adult</name>
    <entry>Poor Maneuverability</entry>
  </collection>
  <collection>
    <name>Blue Dragon, Old</name>
    <entry>Poor Maneuverability</entry>
  </collection>
  <collection>
    <name>Blue Dragon, Very Old</name>
    <entry>Poor Maneuverability</entry>
  </collection>
  <collection>
    <name>Blue Dragon, Very Young</name>
    <entry>Poor Maneuverability</entry>
  </collection>
  <collection>
    <name>Blue Dragon, Wyrm</name>
    <entry>Clumsy Maneuverability</entry>
  </collection>
  <collection>
    <name>Blue Dragon, Wyrmling</name>
    <entry>Average Maneuverability</entry>
  </collection>
  <collection>
    <name>Blue Dragon, Young Adult</name>
    <entry>Poor Maneuverability</entry>
  </collection>
  <collection>
    <name>Blue Dragon, Young</name>
    <entry>Poor Maneuverability</entry>
  </collection>
  <collection>
    <name>Blue Slaad</name>
  </collection>
  <collection>
    <name>Boar</name>
  </collection>
  <collection>
    <name>Bodak</name>
  </collection>
  <collection>
    <name>Bone Devil (Osyluth)</name>
  </collection>
  <collection>
    <name>Bralani</name>
    <entry>Perfect Maneuverability</entry>
  </collection>
  <collection>
    <name>Brass Dragon, Adult</name>
    <entry>Poor Maneuverability</entry>
  </collection>
  <collection>
    <name>Brass Dragon, Ancient</name>
    <entry>Poor Maneuverability</entry>
  </collection>
  <collection>
    <name>Brass Dragon, Great Wyrm</name>
    <entry>Clumsy Maneuverability</entry>
  </collection>
  <collection>
    <name>Brass Dragon, Juvenile</name>
    <entry>Poor Maneuverability</entry>
  </collection>
  <collection>
    <name>Brass Dragon, Mature Adult</name>
    <entry>Poor Maneuverability</entry>
  </collection>
  <collection>
    <name>Brass Dragon, Old</name>
    <entry>Poor Maneuverability</entry>
  </collection>
  <collection>
    <name>Brass Dragon, Very Old</name>
    <entry>Poor Maneuverability</entry>
  </collection>
  <collection>
    <name>Brass Dragon, Very Young</name>
    <entry>Average Maneuverability</entry>
  </collection>
  <collection>
    <name>Brass Dragon, Wyrm</name>
    <entry>Clumsy Maneuverability</entry>
  </collection>
  <collection>
    <name>Brass Dragon, Wyrmling</name>
    <entry>Average Maneuverability</entry>
  </collection>
  <collection>
    <name>Brass Dragon, Young Adult</name>
    <entry>Poor Maneuverability</entry>
  </collection>
  <collection>
    <name>Brass Dragon, Young</name>
    <entry>Poor Maneuverability</entry>
  </collection>
  <collection>
    <name>Bronze Dragon, Adult</name>
    <entry>Poor Maneuverability</entry>
  </collection>
  <collection>
    <name>Bronze Dragon, Ancient</name>
    <entry>Clumsy Maneuverability</entry>
  </collection>
  <collection>
    <name>Bronze Dragon, Great Wyrm</name>
    <entry>Clumsy Maneuverability</entry>
  </collection>
  <collection>
    <name>Bronze Dragon, Juvenile</name>
    <entry>Poor Maneuverability</entry>
  </collection>
  <collection>
    <name>Bronze Dragon, Mature Adult</name>
    <entry>Poor Maneuverability</entry>
  </collection>
  <collection>
    <name>Bronze Dragon, Old</name>
    <entry>Poor Maneuverability</entry>
  </collection>
  <collection>
    <name>Bronze Dragon, Very Old</name>
    <entry>Poor Maneuverability</entry>
  </collection>
  <collection>
    <name>Bronze Dragon, Very Young</name>
    <entry>Poor Maneuverability</entry>
  </collection>
  <collection>
    <name>Bronze Dragon, Wyrm</name>
    <entry>Clumsy Maneuverability</entry>
  </collection>
  <collection>
    <name>Bronze Dragon, Wyrmling</name>
    <entry>Average Maneuverability</entry>
  </collection>
  <collection>
    <name>Bronze Dragon, Young Adult</name>
    <entry>Poor Maneuverability</entry>
  </collection>
  <collection>
    <name>Bronze Dragon, Young</name>
    <entry>Poor Maneuverability</entry>
  </collection>
  <collection>
    <name>Brown Bear</name>
  </collection>
  <collection>
    <name>Bugbear</name>
  </collection>
  <collection>
    <name>Bulette</name>
  </collection>
  <collection>
    <name>Cachalot Whale</name>
  </collection>
  <collection>
    <name>Camel, Bactrian (Two-Humped)</name>
  </collection>
  <collection>
    <name>Camel, Dromedary (One-Humped)</name>
  </collection>
  <collection>
    <name>Carrion Crawler</name>
  </collection>
  <collection>
    <name>Cat</name>
  </collection>
  <collection>
    <name>Centaur</name>
  </collection>
  <collection>
    <name>Centipede Swarm</name>
  </collection>
  <collection>
    <name>Chain Devil (Kyton)</name>
  </collection>
  <collection>
    <name>Chaos Beast</name>
  </collection>
  <collection>
    <name>Chaotic</name>
  </collection>
  <collection>
    <name>Cheetah</name>
  </collection>
  <collection>
    <name>Chimera</name>
    <entry>Poor Maneuverability</entry>
  </collection>
  <collection>
    <name>Choker</name>
  </collection>
  <collection>
    <name>Chuul</name>
    <entry>Skill Bonus#8#Swim: special action or avoid a hazard#0##0</entry>
    <entry>Skill Bonus#10#Swim: can always take 10#0##0</entry>
  </collection>
  <collection>
    <name>Clay Golem</name>
  </collection>
  <collection>
    <name>Cloaker</name>
    <entry>Average Maneuverability</entry>
  </collection>
  <collection>
    <name>Cloud Giant</name>
  </collection>
  <collection>
    <name>Cockatrice</name>
    <entry>Poor Maneuverability</entry>
  </collection>
  <collection>
    <name>Cold</name>
  </collection>
  <collection>
    <name>Constrictor Snake</name>
  </collection>
  <collection>
    <name>Construct</name>
    <entry>Darkvision#60##0##0#False</entry>
    <entry>Immunity#0#Ability Damage#0##0#False</entry>
    <entry>Immunity#0#Ability Drain#0##0#False</entry>
    <entry>Immunity#0#Critical hits#0##0#False</entry>
    <entry>Immunity#0#Death#0##0#False</entry>
    <entry>Immunity#0#Disease#0##0#False</entry>
    <entry>Immunity#0#Energy Drain#0##0#False</entry>
    <entry>Immunity#0#Exhaustion#0##0#False</entry>
    <entry>Immunity#0#Fatigue#0##0#False</entry>
    <entry>Immunity#0#Mind-Affecting Effects#0##0#False</entry>
    <entry>Immunity#0#Necromancy#0##0#False</entry>
    <entry>Immunity#0#Nonlethal damage#0##0#False</entry>
    <entry>Immunity#0#Paralysis#0##0#False</entry>
    <entry>Immunity#0#Poison#0##0#False</entry>
    <entry>Immunity#0#Sleep#0##0#False</entry>
    <entry>Immunity#0#Stunning#0##0#False</entry>
    <entry>Low-Light Vision#0##0##0#False</entry>
  </collection>
  <collection>
    <name>Copper Dragon, Adult</name>
    <entry>Poor Maneuverability</entry>
  </collection>
  <collection>
    <name>Copper Dragon, Ancient</name>
    <entry>Poor Maneuverability</entry>
  </collection>
  <collection>
    <name>Copper Dragon, Great Wyrm</name>
    <entry>Clumsy Maneuverability</entry>
  </collection>
  <collection>
    <name>Copper Dragon, Juvenile</name>
    <entry>Poor Maneuverability</entry>
  </collection>
  <collection>
    <name>Copper Dragon, Mature Adult</name>
    <entry>Poor Maneuverability</entry>
  </collection>
  <collection>
    <name>Copper Dragon, Old</name>
    <entry>Poor Maneuverability</entry>
  </collection>
  <collection>
    <name>Copper Dragon, Very Old</name>
    <entry>Poor Maneuverability</entry>
  </collection>
  <collection>
    <name>Copper Dragon, Very Young</name>
    <entry>Average Maneuverability</entry>
  </collection>
  <collection>
    <name>Copper Dragon, Wyrm</name>
    <entry>Clumsy Maneuverability</entry>
  </collection>
  <collection>
    <name>Copper Dragon, Wyrmling</name>
    <entry>Average Maneuverability</entry>
  </collection>
  <collection>
    <name>Copper Dragon, Young Adult</name>
    <entry>Poor Maneuverability</entry>
  </collection>
  <collection>
    <name>Copper Dragon, Young</name>
    <entry>Poor Maneuverability</entry>
  </collection>
  <collection>
    <name>Couatl</name>
    <entry>Good Maneuverability</entry>
  </collection>
  <collection>
    <name>Criosphinx</name>
    <entry>Poor Maneuverability</entry>
  </collection>
  <collection>
    <name>Crocodile</name>
  </collection>
  <collection>
    <name>Dark Naga</name>
  </collection>
  <collection>
    <name>Darkmantle</name>
    <entry>Poor Maneuverability</entry>
  </collection>
  <collection>
    <name>Death Slaad</name>
  </collection>
  <collection>
    <name>Deep Halfling</name>
  </collection>
  <collection>
    <name>Deep Dwarf</name>
  </collection>
  <collection>
    <name>Deinonychus</name>
  </collection>
  <collection>
    <name>Delver</name>
  </collection>
  <collection>
    <name>Derro</name>
  </collection>
  <collection>
    <name>Derro (Sane)</name>
  </collection>
  <collection>
    <name>Destrachan</name>
  </collection>
  <collection>
    <name>Devourer</name>
  </collection>
  <collection>
    <name>Digester</name>
  </collection>
  <collection>
    <name>Dire Ape</name>
  </collection>
  <collection>
    <name>Dire Badger</name>
  </collection>
  <collection>
    <name>Dire Bat</name>
    <entry>Good Maneuverability</entry>
  </collection>
  <collection>
    <name>Dire Bear</name>
  </collection>
  <collection>
    <name>Dire Boar</name>
  </collection>
  <collection>
    <name>Dire Lion</name>
  </collection>
  <collection>
    <name>Dire Rat</name>
  </collection>
  <collection>
    <name>Dire Shark</name>
  </collection>
  <collection>
    <name>Dire Tiger</name>
  </collection>
  <collection>
    <name>Dire Weasel</name>
  </collection>
  <collection>
    <name>Dire Wolf</name>
  </collection>
  <collection>
    <name>Dire Wolverine</name>
  </collection>
  <collection>
    <name>Displacer Beast</name>
  </collection>
  <collection>
    <name>Displacer Beast Pack Lord</name>
  </collection>
  <collection>
    <name>Djinni</name>
    <entry>Perfect Maneuverability</entry>
  </collection>
  <collection>
    <name>Dog</name>
  </collection>
  <collection>
    <name>Dog, Riding</name>
  </collection>
  <collection>
    <name>Donkey</name>
  </collection>
  <collection>
    <name>Doppelganger</name>
  </collection>
  <collection>
    <name>Dragon</name>
  </collection>
  <collection>
    <name>Dragon Turtle</name>
  </collection>
  <collection>
    <name>Dragonne</name>
    <entry>Poor Maneuverability</entry>
  </collection>
  <collection>
    <name>Dread Wraith</name>
    <entry>Good Maneuverability</entry>
  </collection>
  <collection>
    <name>Dretch</name>
  </collection>
  <collection>
    <name>Drider</name>
  </collection>
  <collection>
    <name>Drow</name>
  </collection>
  <collection>
    <name>Dryad</name>
  </collection>
  <collection>
    <name>Duergar</name>
  </collection>
  <collection>
    <name>Dust Mephit</name>
  </collection>
  <collection>
    <name>Dwarf</name>
  </collection>
  <collection>
    <name>Eagle</name>
    <entry>Average Maneuverability</entry>
  </collection>
  <collection>
    <name>Earth</name>
  </collection>
  <collection>
    <name>Earth Elemental, Elder</name>
  </collection>
  <collection>
    <name>Earth Elemental, Greater</name>
  </collection>
  <collection>
    <name>Earth Elemental, Huge</name>
  </collection>
  <collection>
    <name>Earth Elemental, Large</name>
  </collection>
  <collection>
    <name>Earth Elemental, Medium</name>
  </collection>
  <collection>
    <name>Earth Elemental, Small</name>
  </collection>
  <collection>
    <name>Earth Mephit</name>
  </collection>
  <collection>
    <name>Efreeti</name>
    <entry>Perfect Maneuverability</entry>
  </collection>
  <collection>
    <name>Eight-Headed Cryohydra</name>
  </collection>
  <collection>
    <name>Eight-Headed Hydra</name>
  </collection>
  <collection>
    <name>Eight-Headed Pyrohydra</name>
  </collection>
  <collection>
    <name>Elasmosaurus</name>
  </collection>
  <collection>
    <name>Elder Arrowhawk</name>
  </collection>
  <collection>
    <name>Elder Black Pudding</name>
  </collection>
  <collection>
    <name>Elder Tojanida</name>
  </collection>
  <collection>
    <name>Elder Xorn</name>
  </collection>
  <collection>
    <name>Elemental</name>
  </collection>
  <collection>
    <name>Elephant</name>
  </collection>
  <collection>
    <name>Eleven-Headed Cryohydra</name>
  </collection>
  <collection>
    <name>Eleven-Headed Hydra</name>
  </collection>
  <collection>
    <name>Eleven-Headed Pyrohydra</name>
  </collection>
  <collection>
    <name>Elf</name>
  </collection>
  <collection>
    <name>Erinyes</name>
    <entry>Good Maneuverability</entry>
  </collection>
  <collection>
    <name>Ethereal Filcher</name>
  </collection>
  <collection>
    <name>Ethereal Marauder</name>
  </collection>
  <collection>
    <name>Ettercap</name>
  </collection>
  <collection>
    <name>Ettin</name>
  </collection>
  <collection>
    <name>Evil</name>
  </collection>
  <collection>
    <name>Extraplanar</name>
  </collection>
  <collection>
    <name>Fey</name>
  </collection>
  <collection>
    <name>Fire</name>
  </collection>
  <collection>
    <name>Fire Elemental, Elder</name>
  </collection>
  <collection>
    <name>Fire Elemental, Greater</name>
  </collection>
  <collection>
    <name>Fire Elemental, Huge</name>
  </collection>
  <collection>
    <name>Fire Elemental, Large</name>
  </collection>
  <collection>
    <name>Fire Elemental, Medium</name>
  </collection>
  <collection>
    <name>Fire Elemental, Small</name>
  </collection>
  <collection>
    <name>Fire Giant</name>
  </collection>
  <collection>
    <name>Fire Mephit</name>
  </collection>
  <collection>
    <name>Five-Headed Cryohydra</name>
  </collection>
  <collection>
    <name>Five-Headed Hydra</name>
  </collection>
  <collection>
    <name>Five-Headed Pyrohydra</name>
  </collection>
  <collection>
    <name>Flamebrother Salamander</name>
  </collection>
  <collection>
    <name>Flesh Golem</name>
  </collection>
  <collection>
    <name>Forest Gnome</name>
  </collection>
  <collection>
    <name>Formian Myrmarch</name>
  </collection>
  <collection>
    <name>Formian Queen</name>
  </collection>
  <collection>
    <name>Formian Taskmaster</name>
  </collection>
  <collection>
    <name>Formian Warrior</name>
  </collection>
  <collection>
    <name>Formian Worker</name>
  </collection>
  <collection>
    <name>Frost Giant</name>
  </collection>
  <collection>
    <name>Frost Worm</name>
  </collection>
  <collection>
    <name>Gargoyle</name>
    <entry>Average Maneuverability</entry>
  </collection>
  <collection>
    <name>Gauth (Lesser Beholder)</name>
    <entry>All-Around Vision#0##0##0#False</entry>
    <entry>Flight#0##0##0#False</entry>
    <entry>Skill Bonus#2#Survival: following tracks#0##0#False</entry>
    <entry>Alertness#2##0##0#False</entry>
  </collection>
  <collection>
    <name>Gelatinous Cube</name>
  </collection>
  <collection>
    <name>Ghaele</name>
    <entry>Perfect Maneuverability</entry>
  </collection>
  <collection>
    <name>Ghast</name>
  </collection>
  <collection>
    <name>Ghoul</name>
  </collection>
  <collection>
    <name>Giant</name>
  </collection>
  <collection>
    <name>Giant Ant, Queen</name>
  </collection>
  <collection>
    <name>Giant Ant, Soldier</name>
  </collection>
  <collection>
    <name>Giant Ant, Worker</name>
  </collection>
  <collection>
    <name>Giant Bee</name>
    <entry>Good Maneuverability</entry>
  </collection>
  <collection>
    <name>Giant Bombardier Beetle</name>
  </collection>
  <collection>
    <name>Giant Constrictor Snake</name>
  </collection>
  <collection>
    <name>Giant Crocodile</name>
  </collection>
  <collection>
    <name>Giant Eagle</name>
    <entry>Average Maneuverability</entry>
  </collection>
  <collection>
    <name>Giant Fire Beetle</name>
  </collection>
  <collection>
    <name>Giant Octopus</name>
  </collection>
  <collection>
    <name>Giant Owl</name>
    <entry>Average Maneuverability</entry>
  </collection>
  <collection>
    <name>Giant Praying Mantis</name>
    <entry>Poor Maneuverability</entry>
  </collection>
  <collection>
    <name>Giant Squid</name>
  </collection>
  <collection>
    <name>Giant Stag Beetle</name>
  </collection>
  <collection>
    <name>Giant Wasp</name>
    <entry>Good Maneuverability</entry>
  </collection>
  <collection>
    <name>Gibbering Mouther</name>
  </collection>
  <collection>
    <name>Girallon</name>
  </collection>
  <collection>
    <name>Githyanki</name>
  </collection>
  <collection>
    <name>Githzerai</name>
  </collection>
  <collection>
    <name>Glabrezu</name>
  </collection>
  <collection>
    <name>Gnoll</name>
  </collection>
  <collection>
    <name>Gnome</name>
  </collection>
  <collection>
    <name>Goblin</name>
  </collection>
  <collection>
    <name>Goblinoid</name>
  </collection>
  <collection>
    <name>Gold Dragon, Adult</name>
    <entry>Poor Maneuverability</entry>
  </collection>
  <collection>
    <name>Gold Dragon, Ancient</name>
    <entry>Clumsy Maneuverability</entry>
  </collection>
  <collection>
    <name>Gold Dragon, Great Wyrm</name>
    <entry>Clumsy Maneuverability</entry>
  </collection>
  <collection>
    <name>Gold Dragon, Juvenile</name>
    <entry>Poor Maneuverability</entry>
  </collection>
  <collection>
    <name>Gold Dragon, Mature Adult</name>
    <entry>Poor Maneuverability</entry>
  </collection>
  <collection>
    <name>Gold Dragon, Old</name>
    <entry>Clumsy Maneuverability</entry>
  </collection>
  <collection>
    <name>Gold Dragon, Very Old</name>
    <entry>Clumsy Maneuverability</entry>
  </collection>
  <collection>
    <name>Gold Dragon, Very Young</name>
    <entry>Poor Maneuverability</entry>
  </collection>
  <collection>
    <name>Gold Dragon, Wyrm</name>
    <entry>Clumsy Maneuverability</entry>
  </collection>
  <collection>
    <name>Gold Dragon, Wyrmling</name>
    <entry>Poor Maneuverability</entry>
  </collection>
  <collection>
    <name>Gold Dragon, Young Adult</name>
    <entry>Poor Maneuverability</entry>
  </collection>
  <collection>
    <name>Gold Dragon, Young</name>
    <entry>Poor Maneuverability</entry>
  </collection>
  <collection>
    <name>Good</name>
  </collection>
  <collection>
    <name>Gorgon</name>
  </collection>
  <collection>
    <name>Gray Elf</name>
  </collection>
  <collection>
    <name>Gray Ooze</name>
  </collection>
  <collection>
    <name>Gray Render</name>
  </collection>
  <collection>
    <name>Gray Slaad</name>
  </collection>
  <collection>
    <name>Greater Barghest</name>
  </collection>
  <collection>
    <name>Greater Shadow</name>
    <entry>Good Maneuverability</entry>
  </collection>
  <collection>
    <name>Greater Stone Golem</name>
  </collection>
  <collection>
    <name>Green Dragon, Adult</name>
    <entry>Poor Maneuverability</entry>
  </collection>
  <collection>
    <name>Green Dragon, Ancient</name>
    <entry>Clumsy Maneuverability</entry>
  </collection>
  <collection>
    <name>Green Dragon, Great Wyrm</name>
    <entry>Clumsy Maneuverability</entry>
  </collection>
  <collection>
    <name>Green Dragon, Juvenile</name>
    <entry>Poor Maneuverability</entry>
  </collection>
  <collection>
    <name>Green Dragon, Mature Adult</name>
    <entry>Poor Maneuverability</entry>
  </collection>
  <collection>
    <name>Green Dragon, Old</name>
    <entry>Poor Maneuverability</entry>
  </collection>
  <collection>
    <name>Green Dragon, Very Old</name>
    <entry>Poor Maneuverability</entry>
  </collection>
  <collection>
    <name>Green Dragon, Very Young</name>
    <entry>Poor Maneuverability</entry>
  </collection>
  <collection>
    <name>Green Dragon, Wyrm</name>
    <entry>Clumsy Maneuverability</entry>
  </collection>
  <collection>
    <name>Green Dragon, Wyrmling</name>
    <entry>Average Maneuverability</entry>
  </collection>
  <collection>
    <name>Green Dragon, Young Adult</name>
    <entry>Poor Maneuverability</entry>
  </collection>
  <collection>
    <name>Green Dragon, Young</name>
    <entry>Poor Maneuverability</entry>
  </collection>
  <collection>
    <name>Green Hag</name>
  </collection>
  <collection>
    <name>Green Slaad</name>
  </collection>
  <collection>
    <name>Grick</name>
  </collection>
  <collection>
    <name>Griffon</name>
    <entry>Average Maneuverability</entry>
  </collection>
  <collection>
    <name>Grig</name>
    <entry>Poor Maneuverability</entry>
  </collection>
  <collection>
    <name>Grimlock</name>
  </collection>
  <collection>
    <name>Guardian Naga</name>
  </collection>
  <collection>
    <name>Gynosphinx</name>
    <entry>Poor Maneuverability</entry>
  </collection>
  <collection>
    <name>Half-Elf</name>
  </collection>
  <collection>
    <name>Half-Orc</name>
  </collection>
  <collection>
    <name>Halfling</name>
  </collection>
  <collection>
    <name>Harpy</name>
    <entry>Average Maneuverability</entry>
  </collection>
  <collection>
    <name>Hawk</name>
    <entry>Average Maneuverability</entry>
  </collection>
  <collection>
    <name>Heavy Horse</name>
  </collection>
  <collection>
    <name>Heavy Warhorse</name>
  </collection>
  <collection>
    <name>Hell Hound</name>
  </collection>
  <collection>
    <name>Hellcat (Bezekira)</name>
  </collection>
  <collection>
    <name>Hellwasp Swarm</name>
    <entry>Good Maneuverability</entry>
  </collection>
  <collection>
    <name>Hezrou</name>
  </collection>
  <collection>
    <name>Hieracosphinx</name>
    <entry>Poor Maneuverability</entry>
  </collection>
  <collection>
    <name>High Elf</name>
  </collection>
  <collection>
    <name>Hill Dwarf</name>
  </collection>
  <collection>
    <name>Hill Giant</name>
  </collection>
  <collection>
    <name>Hippogriff</name>
    <entry>Average Maneuverability</entry>
  </collection>
  <collection>
    <name>Hobgoblin</name>
  </collection>
  <collection>
    <name>Homunculus</name>
    <entry>Immunity#0#Ability Damage#0##0</entry>
    <entry>Immunity#0#Ability Drain#0##0</entry>
    <entry>Immunity#0#Critical hits#0##0</entry>
    <entry>Immunity#0#Death#0##0</entry>
    <entry>Immunity#0#Disease#0##0</entry>
    <entry>Immunity#0#Energy Drain#0##0</entry>
    <entry>Immunity#0#Exhaustion#0##0</entry>
    <entry>Immunity#0#Fatigue#0##0</entry>
    <entry>Immunity#0#Mind-Affecting Effects#0##0</entry>
    <entry>Immunity#0#Necromancy#0##0</entry>
    <entry>Immunity#0#Nonlethal damage#0##0</entry>
    <entry>Immunity#0#Paralysis#0##0</entry>
    <entry>Immunity#0#Poison#0##0</entry>
    <entry>Immunity#0#Sleep#0##0</entry>
    <entry>Immunity#0#Stunning#0##0</entry>
  </collection>
  <collection>
    <name>Horned Devil (Cornugon)</name>
    <entry>Average Maneuverability</entry>
  </collection>
  <collection>
    <name>Hound Archon</name>
  </collection>
  <collection>
    <name>Howler</name>
  </collection>
  <collection>
    <name>Human</name>
  </collection>
  <collection>
    <name>Humanoid</name>
  </collection>
  <collection>
    <name>Hyena</name>
  </collection>
  <collection>
    <name>Ice Devil (Gelugon)</name>
  </collection>
  <collection>
    <name>Ice Mephit</name>
  </collection>
  <collection>
    <name>Incorporeal</name>
  </collection>
  <collection>
    <name>Invisible Stalker</name>
    <entry>Perfect Maneuverability</entry>
  </collection>
  <collection>
    <name>Imp</name>
    <entry>Perfect Maneuverability</entry>
  </collection>
  <collection>
    <name>Iron Golem</name>
  </collection>
  <collection>
    <name>Janni</name>
    <entry>Perfect Maneuverability</entry>
  </collection>
  <collection>
    <name>Juvenile Arrowhawk</name>
  </collection>
  <collection>
    <name>Juvenile Tojanida</name>
  </collection>
  <collection>
    <name>Kapoacinth</name>
  </collection>
  <collection>
    <name>Kobold</name>
  </collection>
  <collection>
    <name>Kolyarut</name>
  </collection>
  <collection>
    <name>Kraken</name>
  </collection>
  <collection>
    <name>Krenshar</name>
  </collection>
  <collection>
    <name>Kuo-toa</name>
  </collection>
  <collection>
    <name>Lacedon</name>
  </collection>
  <collection>
    <name>Lamia</name>
  </collection>
  <collection>
    <name>Lammasu</name>
    <entry>Average Maneuverability</entry>
  </collection>
  <collection>
    <name>Lantern Archon</name>
    <entry>Perfect Maneuverability</entry>
  </collection>
  <collection>
    <name>Lawful</name>
  </collection>
  <collection>
    <name>Lemure</name>
  </collection>
  <collection>
    <name>Leonal</name>
  </collection>
  <collection>
    <name>Leopard</name>
  </collection>
  <collection>
    <name>Light Horse</name>
  </collection>
  <collection>
    <name>Light Warhorse</name>
  </collection>
  <collection>
    <name>Lightfoot Halfling</name>
  </collection>
  <collection>
    <name>Lillend</name>
    <entry>Average Maneuverability</entry>
  </collection>
  <collection>
    <name>Lion</name>
  </collection>
  <collection>
    <name>Lizard</name>
  </collection>
  <collection>
    <name>Lizardfolk</name>
  </collection>
  <collection>
    <name>Locathah</name>
  </collection>
  <collection>
    <name>Locust Swarm</name>
    <entry>Poor Maneuverability</entry>
  </collection>
  <collection>
    <name>Magical Beast</name>
  </collection>
  <collection>
    <name>Magma Mephit</name>
    <entry>Average Maneuverability</entry>
  </collection>
  <collection>
    <name>Magmin</name>
  </collection>
  <collection>
    <name>Manta Ray</name>
  </collection>
  <collection>
    <name>Manticore</name>
    <entry>Clumsy Maneuverability</entry>
  </collection>
  <collection>
    <name>Marilith</name>
  </collection>
  <collection>
    <name>Marut</name>
  </collection>
  <collection>
    <name>Medusa</name>
  </collection>
  <collection>
    <name>Megaraptor</name>
  </collection>
  <collection>
    <name>Merfolk</name>
  </collection>
  <collection>
    <name>Merrow</name>
  </collection>
  <collection>
    <name>Mimic</name>
  </collection>
  <collection>
    <name>Mind Flayer (Illithid)</name>
  </collection>
  <collection>
    <name>Minor Xorn</name>
  </collection>
  <collection>
    <name>Minotaur</name>
  </collection>
  <collection>
    <name>Mohrg</name>
  </collection>
  <collection>
    <name>Monitor Lizard</name>
  </collection>
  <collection>
    <name>Monkey</name>
  </collection>
  <collection>
    <name>Monstrous Centipede, Colossal</name>
  </collection>
  <collection>
    <name>Monstrous Centipede, Gargantuan</name>
  </collection>
  <collection>
    <name>Monstrous Centipede, Huge</name>
  </collection>
  <collection>
    <name>Monstrous Centipede, Large</name>
  </collection>
  <collection>
    <name>Monstrous Centipede, Medium</name>
  </collection>
  <collection>
    <name>Monstrous Centipede, Small</name>
  </collection>
  <collection>
    <name>Monstrous Centipede, Tiny</name>
  </collection>
  <collection>
    <name>Monstrous Humanoid</name>
  </collection>
  <collection>
    <name>Monstrous Scorpion, Colossal</name>
  </collection>
  <collection>
    <name>Monstrous Scorpion, Gargantuan</name>
  </collection>
  <collection>
    <name>Monstrous Scorpion, Huge</name>
  </collection>
  <collection>
    <name>Monstrous Scorpion, Large</name>
  </collection>
  <collection>
    <name>Monstrous Scorpion, Medium</name>
  </collection>
  <collection>
    <name>Monstrous Scorpion, Small</name>
  </collection>
  <collection>
    <name>Monstrous Scorpion, Tiny</name>
  </collection>
  <collection>
    <name>Monstrous Spider, Colossal</name>
  </collection>
  <collection>
    <name>Monstrous Spider, Gargantuan</name>
  </collection>
  <collection>
    <name>Monstrous Spider, Huge</name>
  </collection>
  <collection>
    <name>Monstrous Spider, Large</name>
  </collection>
  <collection>
    <name>Monstrous Spider, Medium</name>
  </collection>
  <collection>
    <name>Monstrous Spider, Small</name>
  </collection>
  <collection>
    <name>Monstrous Spider, Tiny</name>
  </collection>
  <collection>
    <name>Mountain Dwarf</name>
  </collection>
  <collection>
    <name>Mule</name>
  </collection>
  <collection>
    <name>Mummy</name>
  </collection>
  <collection>
    <name>Nalfeshnee</name>
    <entry>Poor Maneuverability</entry>
  </collection>
  <collection>
    <name>Native</name>
  </collection>
  <collection>
    <name>Nessian Warhound</name>
  </collection>
  <collection>
    <name>Night Hag</name>
  </collection>
  <collection>
    <name>Nightcrawler</name>
  </collection>
  <collection>
    <name>Nightmare</name>
    <entry>Good Maneuverability</entry>
  </collection>
  <collection>
    <name>Nightmare, Cauchemar</name>
    <entry>Good Maneuverability</entry>
  </collection>
  <collection>
    <name>Nightwalker</name>
    <entry>Poor Maneuverability</entry>
  </collection>
  <collection>
    <name>Nightwing</name>
    <entry>Good Maneuverability</entry>
  </collection>
  <collection>
    <name>Nine-Headed Cryohydra</name>
  </collection>
  <collection>
    <name>Nine-Headed Hydra</name>
  </collection>
  <collection>
    <name>Nine-Headed Pyrohydra</name>
  </collection>
  <collection>
    <name>Nixie</name>
  </collection>
  <collection>
    <name>Noble Djinni</name>
    <entry>Perfect Maneuverability</entry>
  </collection>
  <collection>
    <name>Noble Salamander</name>
  </collection>
  <collection>
    <name>Nymph</name>
  </collection>
  <collection>
    <name>Ochre Jelly</name>
  </collection>
  <collection>
    <name>Octopus</name>
  </collection>
  <collection>
    <name>Ogre</name>
  </collection>
  <collection>
    <name>Ogre Mage</name>
    <entry>Good Maneuverability</entry>
  </collection>
  <collection>
    <name>Ooze</name>
  </collection>
  <collection>
    <name>Ooze Mephit</name>
    <entry>Damage Reduction#5#Vulnerable to magic weapons#1#Hit#0</entry>
    <entry>Darkvision#60##0##0</entry>
    <entry>Fast Healing#2#Exposed to moving air#1#Turn#0</entry>
    <entry>Skill Bonus#2#Disguise: while acting#0##0</entry>
    <entry>Skill Bonus#8#Swim: special action or avoid a hazard#0##0</entry>
    <entry>Skill Bonus#10#Swim: can always take 10#0##0</entry>
    <entry>Skill Bonus#2#Use Rope: with bindings#0##0</entry>
    <entry>Spell-Like Ability#0#Blur#1#Hour#0</entry>
    <entry>Spell-Like Ability#0#Gust of wind#1#Day#0</entry>
  </collection>
  <collection>
    <name>Orc</name>
  </collection>
  <collection>
    <name>Orca Whale</name>
  </collection>
  <collection>
    <name>Otyugh</name>
  </collection>
  <collection>
    <name>Outsider</name>
  </collection>
  <collection>
    <name>Owl</name>
    <entry>Average Maneuverability</entry>
  </collection>
  <collection>
    <name>Owlbear</name>
  </collection>
  <collection>
    <name>Pegasus</name>
    <entry>Average Maneuverability</entry>
  </collection>
  <collection>
    <name>Phantom Fungus</name>
  </collection>
  <collection>
    <name>Phase Spider</name>
  </collection>
  <collection>
    <name>Phasm</name>
  </collection>
  <collection>
    <name>Pit Fiend</name>
    <entry>Average Maneuverability</entry>
  </collection>
  <collection>
    <name>Pixie</name>
    <entry>Good Maneuverability</entry>
  </collection>
  <collection>
    <name>Pixie with Irresistable Dance</name>
    <entry>Good Maneuverability</entry>
  </collection>
  <collection>
    <name>Plant</name>
  </collection>
  <collection>
    <name>Polar Bear</name>
  </collection>
  <collection>
    <name>Pony</name>
  </collection>
  <collection>
    <name>Porpoise</name>
  </collection>
  <collection>
    <name>Pseudodragon</name>
    <entry>Good Maneuverability</entry>
  </collection>
  <collection>
    <name>Purple Worm</name>
  </collection>
  <collection>
    <name>Quasit</name>
    <entry>Perfect Maneuverability</entry>
  </collection>
  <collection>
    <name>Rakshasa</name>
  </collection>
  <collection>
    <name>Rast</name>
    <entry>Good Maneuverability</entry>
  </collection>
  <collection>
    <name>Rat</name>
  </collection>
  <collection>
    <name>Rat Swarm</name>
  </collection>
  <collection>
    <name>Raven</name>
    <entry>Average Maneuverability</entry>
  </collection>
  <collection>
    <name>Ravid</name>
    <entry>Perfect Maneuverability</entry>
  </collection>
  <collection>
    <name>Razor Boar</name>
  </collection>
  <collection>
    <name>Red Dragon, Adult</name>
    <entry>Poor Maneuverability</entry>
  </collection>
  <collection>
    <name>Red Dragon, Ancient</name>
    <entry>Clumsy Maneuverability</entry>
  </collection>
  <collection>
    <name>Red Dragon, Great Wyrm</name>
    <entry>Clumsy Maneuverability</entry>
  </collection>
  <collection>
    <name>Red Dragon, Juvenile</name>
    <entry>Poor Maneuverability</entry>
  </collection>
  <collection>
    <name>Red Dragon, Mature Adult</name>
    <entry>Poor Maneuverability</entry>
  </collection>
  <collection>
    <name>Red Dragon, Old</name>
    <entry>Clumsy Maneuverability</entry>
  </collection>
  <collection>
    <name>Red Dragon, Very Old</name>
    <entry>Clumsy Maneuverability</entry>
  </collection>
  <collection>
    <name>Red Dragon, Very Young</name>
    <entry>Poor Maneuverability</entry>
  </collection>
  <collection>
    <name>Red Dragon, Wyrm</name>
    <entry>Clumsy Maneuverability</entry>
  </collection>
  <collection>
    <name>Red Dragon, Wyrmling</name>
    <entry>Poor Maneuverability</entry>
  </collection>
  <collection>
    <name>Red Dragon, Young Adult</name>
    <entry>Poor Maneuverability</entry>
  </collection>
  <collection>
    <name>Red Dragon, Young</name>
    <entry>Poor Maneuverability</entry>
  </collection>
  <collection>
    <name>Red Slaad</name>
  </collection>
  <collection>
    <name>Remorhaz</name>
  </collection>
  <collection>
    <name>Reptilian</name>
  </collection>
  <collection>
    <name>Retriever</name>
    <entry>Darkvision#60##0##0</entry>
    <entry>Immunity#0#Ability Damage#0##0</entry>
    <entry>Immunity#0#Ability Drain#0##0</entry>
    <entry>Immunity#0#Critical hits#0##0</entry>
    <entry>Immunity#0#Death#0##0</entry>
    <entry>Immunity#0#Disease#0##0</entry>
    <entry>Immunity#0#Energy Drain#0##0</entry>
    <entry>Immunity#0#Exhaustion#0##0</entry>
    <entry>Immunity#0#Fatigue#0##0</entry>
    <entry>Immunity#0#Mind-Affecting Effects#0##0</entry>
    <entry>Immunity#0#Necromancy#0##0</entry>
    <entry>Immunity#0#Nonlethal damage#0##0</entry>
    <entry>Immunity#0#Paralysis#0##0</entry>
    <entry>Immunity#0#Poison#0##0</entry>
    <entry>Immunity#0#Sleep#0##0</entry>
    <entry>Immunity#0#Stunning#0##0</entry>
    <entry>Low-Light Vision#0##0##0</entry>
  </collection>
  <collection>
    <name>Rhinoceras</name>
  </collection>
  <collection>
    <name>Roc</name>
    <entry>Average Maneuverability</entry>
  </collection>
  <collection>
    <name>Rock Gnome</name>
  </collection>
  <collection>
    <name>Roper</name>
  </collection>
  <collection>
    <name>Rust Monster</name>
  </collection>
  <collection>
    <name>Sahuagin</name>
  </collection>
  <collection>
    <name>Sahuagin Mutant</name>
  </collection>
  <collection>
    <name>Malenti</name>
  </collection>
  <collection>
    <name>Salt Mephit</name>
    <entry>Average Maneuverability</entry>
  </collection>
  <collection>
    <name>Satyr</name>
  </collection>
  <collection>
    <name>Satyr with pipes</name>
  </collection>
  <collection>
    <name>Scorpionfolk</name>
  </collection>
  <collection>
    <name>Scrag</name>
  </collection>
  <collection>
    <name>Sea Cat</name>
  </collection>
  <collection>
    <name>Sea Hag</name>
  </collection>
  <collection>
    <name>Seven-Headed Cryohydra</name>
  </collection>
  <collection>
    <name>Seven-Headed Hydra</name>
  </collection>
  <collection>
    <name>Seven-Headed Pyrohydra</name>
  </collection>
  <collection>
    <name>Shadow</name>
    <entry>Good Maneuverability</entry>
  </collection>
  <collection>
    <name>Shadow Mastiff</name>
  </collection>
  <collection>
    <name>Shambling Mound</name>
  </collection>
  <collection>
    <name>Shapechanger</name>
  </collection>
  <collection>
    <name>Shark, Huge</name>
  </collection>
  <collection>
    <name>Shark, Large</name>
  </collection>
  <collection>
    <name>Shark, Medium</name>
  </collection>
  <collection>
    <name>Shield Guardian</name>
  </collection>
  <collection>
    <name>Shocker Lizard</name>
  </collection>
  <collection>
    <name>Shrieker</name>
  </collection>
  <collection>
    <name>Silver Dragon, Adult</name>
    <entry>Poor Maneuverability</entry>
  </collection>
  <collection>
    <name>Silver Dragon, Ancient</name>
    <entry>Clumsy Maneuverability</entry>
  </collection>
  <collection>
    <name>Silver Dragon, Great Wyrm</name>
    <entry>Clumsy Maneuverability</entry>
  </collection>
  <collection>
    <name>Silver Dragon, Juvenile</name>
    <entry>Poor Maneuverability</entry>
  </collection>
  <collection>
    <name>Silver Dragon, Mature Adult</name>
    <entry>Poor Maneuverability</entry>
  </collection>
  <collection>
    <name>Silver Dragon, Old</name>
    <entry>Poor Maneuverability</entry>
  </collection>
  <collection>
    <name>Silver Dragon, Very Old</name>
    <entry>Poor Maneuverability</entry>
  </collection>
  <collection>
    <name>Silver Dragon, Very Young</name>
    <entry>Poor Maneuverability</entry>
  </collection>
  <collection>
    <name>Silver Dragon, Wyrm</name>
    <entry>Clumsy Maneuverability</entry>
  </collection>
  <collection>
    <name>Silver Dragon, Wyrmling</name>
    <entry>Average Maneuverability</entry>
  </collection>
  <collection>
    <name>Silver Dragon, Young Adult</name>
    <entry>Poor Maneuverability</entry>
  </collection>
  <collection>
    <name>Silver Dragon, Young</name>
    <entry>Poor Maneuverability</entry>
  </collection>
  <collection>
    <name>Six-Headed Cryohydra</name>
  </collection>
  <collection>
    <name>Six-Headed Hydra</name>
  </collection>
  <collection>
    <name>Six-Headed Pyrohydra</name>
  </collection>
  <collection>
    <name>Skum</name>
  </collection>
  <collection>
    <name>Spectre</name>
    <entry>Perfect Maneuverability</entry>
  </collection>
  <collection>
    <name>Spider Eater</name>
    <entry>Good Maneuverability</entry>
  </collection>
  <collection>
    <name>Spider Swarm</name>
  </collection>
  <collection>
    <name>Spirit Naga</name>
  </collection>
  <collection>
    <name>Squid</name>
  </collection>
  <collection>
    <name>Steam Mephit</name>
    <entry>Average Maneuverability</entry>
  </collection>
  <collection>
    <name>Stirge</name>
    <entry>Average Maneuverability</entry>
  </collection>
  <collection>
    <name>Stone Giant</name>
  </collection>
  <collection>
    <name>Stone Giant Elder</name>
  </collection>
  <collection>
    <name>Stone Golem</name>
  </collection>
  <collection>
    <name>Storm Giant</name>
  </collection>
  <collection>
    <name>Succubus</name>
    <entry>Average Maneuverability</entry>
  </collection>
  <collection>
    <name>Svirfneblin</name>
  </collection>
  <collection>
    <name>Swarm</name>
  </collection>
  <collection>
    <name>Tallfellow Halfling</name>
  </collection>
  <collection>
    <name>Tarrasque</name>
  </collection>
  <collection>
    <name>Ten-Headed Cryohydra</name>
  </collection>
  <collection>
    <name>Ten-Headed Hydra</name>
  </collection>
  <collection>
    <name>Ten-Headed Pyrohydra</name>
  </collection>
  <collection>
    <name>Tendriculos</name>
  </collection>
  <collection>
    <name>Thoqqua</name>
  </collection>
  <collection>
    <name>Tiefling</name>
  </collection>
  <collection>
    <name>Tiger</name>
  </collection>
  <collection>
    <name>Titan</name>
  </collection>
  <collection>
    <name>Toad</name>
  </collection>
  <collection>
    <name>Treant</name>
  </collection>
  <collection>
    <name>Triceratops</name>
  </collection>
  <collection>
    <name>Triton</name>
  </collection>
  <collection>
    <name>Troglodyte</name>
  </collection>
  <collection>
    <name>Troll</name>
  </collection>
  <collection>
    <name>Truly Horrid Umber Hulk</name>
  </collection>
  <collection>
    <name>Trumpet Archon</name>
    <entry>Good Maneuverability</entry>
  </collection>
  <collection>
    <name>Twelve-Headed Cryohydra</name>
  </collection>
  <collection>
    <name>Twelve-Headed Hydra</name>
  </collection>
  <collection>
    <name>Twelve-Headed Pyrohydra</name>
  </collection>
  <collection>
    <name>Tyrannosaurus</name>
  </collection>
  <collection>
    <name>Umber Hulk</name>
  </collection>
  <collection>
    <name>Undead</name>
  </collection>
  <collection>
    <name>Unicorn</name>
  </collection>
  <collection>
    <name>Vampire Spawn</name>
  </collection>
  <collection>
    <name>Vargouille</name>
    <entry>Good Maneuverability</entry>
  </collection>
  <collection>
    <name>Vermin</name>
  </collection>
  <collection>
    <name>Violet Fungus</name>
  </collection>
  <collection>
    <name>Viper Snake, Huge</name>
  </collection>
  <collection>
    <name>Viper Snake, Large</name>
  </collection>
  <collection>
    <name>Viper Snake, Medium</name>
  </collection>
  <collection>
    <name>Viper Snake, Small</name>
  </collection>
  <collection>
    <name>Viper Snake, Tiny</name>
  </collection>
  <collection>
    <name>Vrock</name>
    <entry>Average Maneuverability</entry>
  </collection>
  <collection>
    <name>Warpony</name>
  </collection>
  <collection>
    <name>Water</name>
  </collection>
  <collection>
    <name>Water Elemental, Elder</name>
  </collection>
  <collection>
    <name>Water Elemental, Greater</name>
  </collection>
  <collection>
    <name>Water Elemental, Huge</name>
  </collection>
  <collection>
    <name>Water Elemental, Large</name>
  </collection>
  <collection>
    <name>Water Elemental, Medium</name>
  </collection>
  <collection>
    <name>Water Elemental, Small</name>
  </collection>
  <collection>
    <name>Water Mephit</name>
    <entry>Damage Reduction#5#Vulnerable to magic weapons#1#Hit#0</entry>
    <entry>Darkvision#60##0##0</entry>
    <entry>Fast Healing#2#Exposed to moving air#1#Turn#0</entry>
    <entry>Skill Bonus#2#Disguise: while acting#0##0</entry>
    <entry>Skill Bonus#8#Swim: special action or avoid a hazard#0##0</entry>
    <entry>Skill Bonus#10#Swim: can always take 10#0##0</entry>
    <entry>Skill Bonus#2#Use Rope: with bindings#0##0</entry>
    <entry>Spell-Like Ability#0#Blur#1#Hour#0</entry>
    <entry>Spell-Like Ability#0#Gust of wind#1#Day#0</entry>
  </collection>
  <collection>
    <name>Water Naga</name>
  </collection>
  <collection>
    <name>Weasel</name>
  </collection>
  <collection>
    <name>White Dragon, Adult</name>
    <entry>Poor Maneuverability</entry>
  </collection>
  <collection>
    <name>White Dragon, Ancient</name>
    <entry>Poor Maneuverability</entry>
  </collection>
  <collection>
    <name>White Dragon, Great Wyrm</name>
    <entry>Clumsy Maneuverability</entry>
  </collection>
  <collection>
    <name>White Dragon, Juvenile</name>
    <entry>Poor Maneuverability</entry>
  </collection>
  <collection>
    <name>White Dragon, Mature Adult</name>
    <entry>Poor Maneuverability</entry>
  </collection>
  <collection>
    <name>White Dragon, Old</name>
    <entry>Poor Maneuverability</entry>
  </collection>
  <collection>
    <name>White Dragon, Very Old</name>
    <entry>Poor Maneuverability</entry>
  </collection>
  <collection>
    <name>White Dragon, Very Young</name>
    <entry>Average Maneuverability</entry>
  </collection>
  <collection>
    <name>White Dragon, Wyrm</name>
    <entry>Clumsy Maneuverability</entry>
  </collection>
  <collection>
    <name>White Dragon, Wyrmling</name>
    <entry>Average Maneuverability</entry>
  </collection>
  <collection>
    <name>White Dragon, Young Adult</name>
    <entry>Poor Maneuverability</entry>
  </collection>
  <collection>
    <name>White Dragon, Young</name>
    <entry>Poor Maneuverability</entry>
  </collection>
  <collection>
    <name>Wight</name>
  </collection>
  <collection>
    <name>Wild Elf</name>
  </collection>
  <collection>
    <name>Will-O'-Wisp</name>
    <entry>Perfect Maneuverability</entry>
  </collection>
  <collection>
    <name>Winter Wolf</name>
  </collection>
  <collection>
    <name>Wolf</name>
  </collection>
  <collection>
    <name>Wolverine</name>
  </collection>
  <collection>
    <name>Worg</name>
  </collection>
  <collection>
    <name>Wood Elf</name>
  </collection>
  <collection>
    <name>Wraith</name>
    <entry>Good Maneuverability</entry>
  </collection>
  <collection>
    <name>Wyvern</name>
    <entry>Poor Maneuverability</entry>
  </collection>
  <collection>
    <name>Xill</name>
  </collection>
  <collection>
    <name>Yeth Hound</name>
    <entry>Good Maneuverability</entry>
  </collection>
  <collection>
    <name>Yrthak</name>
    <entry>Average Maneuverability</entry>
  </collection>
  <collection>
    <name>Yuan-ti Abomination</name>
  </collection>
  <collection>
    <name>Yuan-ti Halfblood</name>
  </collection>
  <collection>
    <name>Yuan-ti Pureblood</name>
  </collection>
  <collection>
    <name>Zelekhut</name>
    <entry>Average Maneuverability</entry>
  </collection>
</collections>