<?xml version="1.0" encoding="utf-8" ?>

<collections>
    <collection>
        <name>Martial Weapon Proficiency</name>
        <entry>Martial Weapon Proficiency</entry>
        <entry>0</entry>
        <entry>All</entry>
        <entry>0</entry>
        <entry>0</entry>
        <entry></entry>
        <entry>0</entry>
        <entry></entry>
      <entry></entry>
      <entry>False</entry>
    </collection>
  <collection>
    <name>Weapon Focus</name>
    <entry>Weapon Focus</entry>
    <entry>0</entry>
    <entry>Weapons with unarmed, grapple, and ray</entry>
    <entry>0</entry>
    <entry>0</entry>
    <entry></entry>
    <entry>0</entry>
    <entry></entry>
    <entry></entry>
    <entry>False</entry>
  </collection>
</collections>